flags/__init__.py
bashflags.py-0.0.1.dist-info/METADATA
bashflags.py-0.0.1.dist-info/WHEEL
bashflags.py-0.0.1.dist-info/top_level.txt
bashflags.py-0.0.1.dist-info/RECORD
