Metadata-Version: 2.1
Name: bashflags.py
Version: 0.0.1
Summary: Parse bash flags
Home-page: http://github.com/Ehnryu/flags
Author: Ehnryu/Sakurai07
Author-email: blzzardst0rm@gmail.com
License: MIT
Keywords: flags,argparse,getopt
Platform: UNKNOWN
